cli_main.py
gitfun/GitFun.py
gitfun/__init__.py
gitfun/__main__.py
gitfun-0.0.8.17.dist-info/LICENSE
gitfun-0.0.8.17.dist-info/METADATA
gitfun-0.0.8.17.dist-info/WHEEL
gitfun-0.0.8.17.dist-info/entry_points.txt
gitfun-0.0.8.17.dist-info/top_level.txt
gitfun-0.0.8.17.dist-info/RECORD
