Metadata-Version: 2.1
Name: gitfun
Version: 0.0.8.17
Summary: Make Git simplified for lazy developers 
Home-page: https://github.com/memetics19/gitfun.git
Author: Shreeda Bhat
Author-email: shreeda@astaqc.com
License: MIT
Platform: UNKNOWN
Classifier: Programming Language :: Python :: 3.8
Classifier: Operating System :: OS Independent
Requires-Python: >=3.7
Requires-Dist: bleach (==3.3.0)
Requires-Dist: certifi (==2020.12.5)
Requires-Dist: cffi (==1.14.5)
Requires-Dist: chardet (==4.0.0)
Requires-Dist: click (==7.1.2)
Requires-Dist: colorama (==0.4.4)
Requires-Dist: Deprecated (==1.2.12)
Requires-Dist: docutils (==0.17.1)
Requires-Dist: idna (==2.10)
Requires-Dist: importlib-metadata (==4.0.1)
Requires-Dist: keyring (==23.0.1)
Requires-Dist: packaging (==20.9)
Requires-Dist: pkginfo (==1.7.0)
Requires-Dist: pycparser (==2.20)
Requires-Dist: PyGithub (==1.55)
Requires-Dist: Pygments (==2.8.1)
Requires-Dist: PyJWT (==2.1.0)
Requires-Dist: PyNaCl (==1.4.0)
Requires-Dist: pyparsing (==2.4.7)
Requires-Dist: readme-renderer (==29.0)
Requires-Dist: requests (==2.25.1)
Requires-Dist: requests-toolbelt (==0.9.1)
Requires-Dist: rfc3986 (==1.4.0)
Requires-Dist: six (==1.15.0)
Requires-Dist: tqdm (==4.60.0)
Requires-Dist: twine (==3.4.1)
Requires-Dist: urllib3 (==1.26.5)
Requires-Dist: webencodings (==0.5.1)
Requires-Dist: wrapt (==1.12.1)
Requires-Dist: zipp (==3.4.1)
